wind_stats/__init__.py
wind_stats/__version__.py
wind_stats/constants.py
wind_stats/geometry.py
wind_stats/gwa_reader.py
wind_stats/models.py
wind_stats/py.typed
wind_stats/stats.py
wind_stats/units.py
wind_stats/utils.py
wind_stats-0.3.1.dist-info/METADATA
wind_stats-0.3.1.dist-info/WHEEL
wind_stats-0.3.1.dist-info/licenses/LICENSE
wind_stats-0.3.1.dist-info/RECORD
