Metadata-Version: 2.4
Name: wind-stats
Version: 0.3.1
Summary: Statistics tools to evaluate your wind energy projects
Project-URL: Homepage, https://github.com/jules-ch/wind-stats
Project-URL: Documentation, https://wind-stats.readthedocs.io/
Maintainer-email: Jules Chéron <jules.cheron@gmail.com>
License-Expression: MIT
License-File: LICENSE
Keywords: energy,renewables,statistics,wind
Classifier: Development Status :: 3 - Alpha
Classifier: Intended Audience :: Science/Research
Classifier: License :: OSI Approved :: MIT License
Classifier: Natural Language :: English
Classifier: Operating System :: OS Independent
Classifier: Programming Language :: Python :: 3.8
Classifier: Programming Language :: Python :: 3.9
Classifier: Programming Language :: Python :: 3.10
Classifier: Programming Language :: Python :: 3.11
Classifier: Programming Language :: Python :: 3.12
Classifier: Topic :: Scientific/Engineering
Classifier: Topic :: Scientific/Engineering :: Physics
Requires-Python: >=3.8
Requires-Dist: numpy>=1.21
Requires-Dist: pandas
Requires-Dist: pint
Requires-Dist: scipy
Requires-Dist: xarray
Provides-Extra: dev
Requires-Dist: black>=23.1.0; extra == 'dev'
Requires-Dist: isort>=5.6.4; extra == 'dev'
Requires-Dist: mypy>=1.0.0; extra == 'dev'
Requires-Dist: ruff; extra == 'dev'
Requires-Dist: types-requests; extra == 'dev'
Provides-Extra: test
Requires-Dist: pytest-cov; extra == 'test'
Requires-Dist: pytest>=7.0.0; extra == 'test'
Requires-Dist: requests; extra == 'test'
Requires-Dist: responses; extra == 'test'
